.cvsignore
bootstrap.py
buildout.cfg
setup.py
z3c/__init__.py
z3c.recipe.ldap.egg-info/PKG-INFO
z3c.recipe.ldap.egg-info/SOURCES.txt
z3c.recipe.ldap.egg-info/dependency_links.txt
z3c.recipe.ldap.egg-info/entry_points.txt
z3c.recipe.ldap.egg-info/namespace_packages.txt
z3c.recipe.ldap.egg-info/requires.txt
z3c.recipe.ldap.egg-info/top_level.txt
z3c.recipe.ldap.egg-info/zip-safe
z3c/recipe/__init__.py
z3c/recipe/ldap/README.txt
z3c/recipe/ldap/__init__.py
z3c/recipe/ldap/conf.py
z3c/recipe/ldap/ctl.py
z3c/recipe/ldap/slapadd.py
z3c/recipe/ldap/slapd.py
z3c/recipe/ldap/docs/README.txt
z3c/recipe/ldap/tests/__init__.py
z3c/recipe/ldap/tests/test_docs.py
