Metadata-Version: 1.0
Name: z3c.recipe.ldap
Version: 0.1
Summary: Deploy an OpenLDAP server in a zc.buildout
Home-page: http://pypi.python.org/pypi/z3c.recipe.ldap
Author: Ross Patterson
Author-email: me@rpatterson.net
License: ZPL
Platform: UNKNOWN
Classifier: Programming Language :: Python
Classifier: Topic :: Software Development :: Libraries :: Python Modules
